llmstruct/__init__.py
llmstruct/core.py
llmstruct-0.1.1.dist-info/licenses/LICENSE
llmstruct-0.1.1.dist-info/METADATA
llmstruct-0.1.1.dist-info/WHEEL
llmstruct-0.1.1.dist-info/top_level.txt
llmstruct-0.1.1.dist-info/RECORD
