Metadata-Version: 2.4
Name: llmstruct
Version: 0.1.1
Summary: A Python library for reliably extracting structured JSON from text and validating it with Pydantic models.
Author-email: Jan Philip Göpfert <janphilip@gopfert.eu>
License: MIT License
Requires-Python: >=3.13
License-File: LICENSE
Requires-Dist: pydantic>=2.0
Provides-Extra: dev
Requires-Dist: pytest>=8.3.5; extra == "dev"
Provides-Extra: demos
Requires-Dist: tenacity>=9.1.2; extra == "demos"
Requires-Dist: anthropic>=0.28.0; extra == "demos"
Requires-Dist: httpx>=0.27.0; extra == "demos"
Dynamic: license-file
